<annotation><filename>CTR_286.jpg</filename><origin>/home/cmast/Documents/Eduardo/sw/MobileDet-TF1/dataset/Backup/train/DSC08131.jpg</origin><path>/home/cmast/Documents/Eduardo/sw/MobileDet-TF1/dataset/640x480/train/Peach_2021_11_11_945176_dmwm.jpg</path><source><database>Peach</database></source><size><height>480</height><width>640</width><depth>3</depth></size><data_augmentation><type>Unspecified</type></data_augmentation><segmented>0</segmented><object><name>peach</name><pose>Unspecified</pose><truncated>0</truncated><difficult>0</difficult><bndbox><xmin>272</xmin><ymin>23</ymin><xmax>311</xmax><ymax>65</ymax></bndbox></object><object><name>peach</name><pose>Unspecified</pose><truncated>0</truncated><difficult>0</difficult><bndbox><xmin>407</xmin><ymin>68</ymin><xmax>443</xmax><ymax>98</ymax></bndbox></object><object><name>peach</name><pose>Unspecified</pose><truncated>0</truncated><difficult>0</difficult><bndbox><xmin>435</xmin><ymin>107</ymin><xmax>471</xmax><ymax>142</ymax></bndbox></object><object><name>peach</name><pose>Unspecified</pose><truncated>0</truncated><difficult>0</difficult><bndbox><xmin>418</xmin><ymin>132</ymin><xmax>452</xmax><ymax>161</ymax></bndbox></object><object><name>peach</name><pose>Unspecified</pose><truncated>0</truncated><difficult>0</difficult><bndbox><xmin>304</xmin><ymin>255</ymin><xmax>336</xmax><ymax>288</ymax></bndbox></object><object><name>peach</name><pose>Unspecified</pose><truncated>0</truncated><difficult>0</difficult><bndbox><xmin>484</xmin><ymin>274</ymin><xmax>521</xmax><ymax>311</ymax></bndbox></object><object><name>peach</name><pose>Unspecified</pose><truncated>0</truncated><difficult>0</difficult><bndbox><xmin>503</xmin><ymin>296</ymin><xmax>539</xmax><ymax>336</ymax></bndbox></object><object><name>peach</name><pose>Unspecified</pose><truncated>0</truncated><difficult>0</difficult><bndbox><xmin>476</xmin><ymin>311</ymin><xmax>514</xmax><ymax>351</ymax></bndbox></object><object><name>peach</name><pose>Unspecified</pose><truncated>0</truncated><difficult>0</difficult><bndbox><xmin>472</xmin><ymin>353</ymin><xmax>511</xmax><ymax>391</ymax></bndbox></object><object><name>peach</name><pose>Unspecified</pose><truncated>0</truncated><difficult>0</difficult><bndbox><xmin>432</xmin><ymin>280</ymin><xmax>455</xmax><ymax>307</ymax></bndbox></object><object><name>peach</name><pose>Unspecified</pose><truncated>0</truncated><difficult>0</difficult><bndbox><xmin>400</xmin><ymin>306</ymin><xmax>426</xmax><ymax>329</ymax></bndbox></object><object><name>peach</name><pose>Unspecified</pose><truncated>0</truncated><difficult>0</difficult><bndbox><xmin>574</xmin><ymin>205</ymin><xmax>595</xmax><ymax>230</ymax></bndbox></object><object><name>peach</name><pose>Unspecified</pose><truncated>0</truncated><difficult>0</difficult><bndbox><xmin>532</xmin><ymin>50</ymin><xmax>554</xmax><ymax>72</ymax></bndbox></object><object><name>peach</name><pose>Unspecified</pose><truncated>0</truncated><difficult>0</difficult><bndbox><xmin>543</xmin><ymin>70</ymin><xmax>561</xmax><ymax>94</ymax></bndbox></object><object><name>peach</name><pose>Unspecified</pose><truncated>0</truncated><difficult>0</difficult><bndbox><xmin>588</xmin><ymin>176</ymin><xmax>607</xmax><ymax>196</ymax></bndbox></object><object><name>peach</name><pose>Unspecified</pose><truncated>0</truncated><difficult>0</difficult><bndbox><xmin>502</xmin><ymin>357</ymin><xmax>536</xmax><ymax>387</ymax></bndbox></object><object><name>peach</name><pose>Unspecified</pose><truncated>0</truncated><difficult>0</difficult><bndbox><xmin>405</xmin><ymin>287</ymin><xmax>429</xmax><ymax>312</ymax></bndbox></object><object><name>peach</name><pose>Unspecified</pose><truncated>0</truncated><difficult>0</difficult><bndbox><xmin>598</xmin><ymin>165</ymin><xmax>615</xmax><ymax>183</ymax></bndbox></object></annotation>