<annotation><filename>CTR_114.jpg</filename><origin>/home/cmast/Documents/Eduardo/sw/MobileDet-TF1/dataset/Backup/train/DSC08178.jpg</origin><path>/home/cmast/Documents/Eduardo/sw/MobileDet-TF1/dataset/640x480/train/Peach_2021_11_11_505981_fndk.jpg</path><source><database>Peach</database></source><size><height>480</height><width>640</width><depth>3</depth></size><data_augmentation><type>Unspecified</type></data_augmentation><segmented>0</segmented><object><name>peach</name><pose>Unspecified</pose><truncated>0</truncated><difficult>0</difficult><bndbox><xmin>122</xmin><ymin>47</ymin><xmax>159</xmax><ymax>85</ymax></bndbox></object><object><name>peach</name><pose>Unspecified</pose><truncated>0</truncated><difficult>0</difficult><bndbox><xmin>182</xmin><ymin>264</ymin><xmax>211</xmax><ymax>292</ymax></bndbox></object><object><name>peach</name><pose>Unspecified</pose><truncated>0</truncated><difficult>0</difficult><bndbox><xmin>432</xmin><ymin>109</ymin><xmax>456</xmax><ymax>135</ymax></bndbox></object><object><name>peach</name><pose>Unspecified</pose><truncated>0</truncated><difficult>0</difficult><bndbox><xmin>429</xmin><ymin>17</ymin><xmax>453</xmax><ymax>44</ymax></bndbox></object><object><name>peach</name><pose>Unspecified</pose><truncated>0</truncated><difficult>0</difficult><bndbox><xmin>457</xmin><ymin>16</ymin><xmax>485</xmax><ymax>42</ymax></bndbox></object><object><name>peach</name><pose>Unspecified</pose><truncated>0</truncated><difficult>0</difficult><bndbox><xmin>303</xmin><ymin>305</ymin><xmax>324</xmax><ymax>327</ymax></bndbox></object><object><name>peach</name><pose>Unspecified</pose><truncated>0</truncated><difficult>0</difficult><bndbox><xmin>313</xmin><ymin>335</ymin><xmax>332</xmax><ymax>354</ymax></bndbox></object><object><name>peach</name><pose>Unspecified</pose><truncated>0</truncated><difficult>0</difficult><bndbox><xmin>302</xmin><ymin>354</ymin><xmax>322</xmax><ymax>375</ymax></bndbox></object><object><name>peach</name><pose>Unspecified</pose><truncated>0</truncated><difficult>0</difficult><bndbox><xmin>267</xmin><ymin>265</ymin><xmax>287</xmax><ymax>286</ymax></bndbox></object><object><name>peach</name><pose>Unspecified</pose><truncated>0</truncated><difficult>0</difficult><bndbox><xmin>310</xmin><ymin>270</ymin><xmax>329</xmax><ymax>289</ymax></bndbox></object><object><name>peach</name><pose>Unspecified</pose><truncated>0</truncated><difficult>0</difficult><bndbox><xmin>68</xmin><ymin>221</ymin><xmax>98</xmax><ymax>246</ymax></bndbox></object><object><name>peach</name><pose>Unspecified</pose><truncated>0</truncated><difficult>0</difficult><bndbox><xmin>385</xmin><ymin>117</ymin><xmax>404</xmax><ymax>142</ymax></bndbox></object></annotation>