<annotation><filename>RT_197.jpg</filename><origin>/home/cmast/Documents/Eduardo/sw/MobileDet-TF1/dataset/Backup/train/DSC08238.jpg</origin><path>/home/cmast/Documents/Eduardo/sw/MobileDet-TF1/dataset/640x480/train/Peach_2021_11_11_821698_ppxb.jpg</path><source><database>Peach</database></source><size><height>480</height><width>640</width><depth>3</depth></size><data_augmentation><type>Unspecified</type></data_augmentation><segmented>0</segmented><object><name>peach</name><pose>Unspecified</pose><truncated>0</truncated><difficult>0</difficult><bndbox><xmin>45</xmin><ymin>172</ymin><xmax>99</xmax><ymax>222</ymax></bndbox></object><object><name>peach</name><pose>Unspecified</pose><truncated>0</truncated><difficult>0</difficult><bndbox><xmin>382</xmin><ymin>42</ymin><xmax>437</xmax><ymax>96</ymax></bndbox></object><object><name>peach</name><pose>Unspecified</pose><truncated>0</truncated><difficult>0</difficult><bndbox><xmin>166</xmin><ymin>263</ymin><xmax>196</xmax><ymax>294</ymax></bndbox></object><object><name>peach</name><pose>Unspecified</pose><truncated>0</truncated><difficult>0</difficult><bndbox><xmin>508</xmin><ymin>402</ymin><xmax>553</xmax><ymax>446</ymax></bndbox></object><object><name>peach</name><pose>Unspecified</pose><truncated>0</truncated><difficult>0</difficult><bndbox><xmin>37</xmin><ymin>382</ymin><xmax>67</xmax><ymax>408</ymax></bndbox></object><object><name>peach</name><pose>Unspecified</pose><truncated>0</truncated><difficult>0</difficult><bndbox><xmin>1</xmin><ymin>93</ymin><xmax>22</xmax><ymax>135</ymax></bndbox></object></annotation>